duckduckgo_images_api/__init__.py
duckduckgo_images_api/api.py
duckduckgo_images_api-1.0.0.dist-info/LICENSE
duckduckgo_images_api-1.0.0.dist-info/METADATA
duckduckgo_images_api-1.0.0.dist-info/WHEEL
duckduckgo_images_api-1.0.0.dist-info/top_level.txt
duckduckgo_images_api-1.0.0.dist-info/zip-safe
duckduckgo_images_api-1.0.0.dist-info/RECORD
