Metadata-Version: 2.1
Name: duckduckgo-images-api
Version: 1.0.0
Summary: DuckDuckGo Image Search Results - using Python !
Home-page: https://github.com/joeyism/duckduckgo-images-api
Author: joeyism
License: MIT
Keywords: duckduckgo image api
Platform: UNKNOWN
Requires-Dist: requests (>=2.18.4)
